[{"constant":true,"inputs":[{"name":"shortId","type":"bytes4"}],"name":"getItemId","outputs":[{"name":"","type":"bytes32"}],"payable":false,"stateMutability":"view","type":"function"},{"constant":false,"inputs":[{"name":"itemId","type":"bytes32"}],"name":"createShortId","outputs":[{"name":"shortId","type":"bytes4"}],"payable":false,"stateMutability":"nonpayable","type":"function"},{"constant":true,"inputs":[{"name":"itemId","type":"bytes32"}],"name":"getShortId","outputs":[{"name":"","type":"bytes4"}],"payable":false,"stateMutability":"view","type":"function"},{"anonymous":false,"inputs":[{"indexed":true,"name":"itemId","type":"bytes32"},{"indexed":false,"name":"shortId","type":"bytes32"}],"name":"CreateShortId","type":"event"}]